testdump/__init__.py
testdump/monitoring.py
testdump-0.1.0.dist-info/LICENSE
testdump-0.1.0.dist-info/METADATA
testdump-0.1.0.dist-info/WHEEL
testdump-0.1.0.dist-info/top_level.txt
testdump-0.1.0.dist-info/RECORD
