Metadata-Version: 2.1
Name: testdump
Version: 0.1.0
Author: Durbar Chakraborty
Author-email: durbardibyo@gmail.com
License-File: LICENSE
Requires-Dist: prometheus-client (>=0.14.1)
